odoo8_addon_sale_commercial_partner-8.0.1.0.0.99.dev3-nspkg.pth
odoo_addons/sale_commercial_partner/README.rst
odoo_addons/sale_commercial_partner/__init__.py
odoo_addons/sale_commercial_partner/__openerp__.py
odoo_addons/sale_commercial_partner/i18n/sale_commercial_partner.pot
odoo_addons/sale_commercial_partner/models/__init__.py
odoo_addons/sale_commercial_partner/models/sale.py
odoo_addons/sale_commercial_partner/report/__init__.py
odoo_addons/sale_commercial_partner/report/sale_report.py
odoo_addons/sale_commercial_partner/report/sale_report_view.xml
odoo_addons/sale_commercial_partner/static/description/icon.png
odoo_addons/sale_commercial_partner/views/sale.xml
odoo8_addon_sale_commercial_partner-8.0.1.0.0.99.dev3.dist-info/METADATA
odoo8_addon_sale_commercial_partner-8.0.1.0.0.99.dev3.dist-info/WHEEL
odoo8_addon_sale_commercial_partner-8.0.1.0.0.99.dev3.dist-info/namespace_packages.txt
odoo8_addon_sale_commercial_partner-8.0.1.0.0.99.dev3.dist-info/top_level.txt
odoo8_addon_sale_commercial_partner-8.0.1.0.0.99.dev3.dist-info/RECORD
